{
	"name": "pl_ingest_cases_deaths",
	"properties": {
		"activities": [
			{
				"name": "copy cases deaths",
				"type": "Copy",
				"dependsOn": [],
				"policy": {
					"timeout": "7.00:00:00",
					"retry": 0,
					"retryIntervalInSeconds": 30,
					"secureOutput": false,
					"secureInput": false
				},
				"userProperties": [],
				"typeProperties": {
					"source": {
						"type": "DelimitedTextSource",
						"storeSettings": {
							"type": "HttpReadSettings",
							"requestMethod": "GET"
						},
						"formatSettings": {
							"type": "DelimitedTextReadSettings"
						}
					},
					"sink": {
						"type": "DelimitedTextSink",
						"storeSettings": {
							"type": "AzureBlobFSWriteSettings"
						},
						"formatSettings": {
							"type": "DelimitedTextWriteSettings",
							"quoteAllText": true,
							"fileExtension": ".txt"
						}
					},
					"enableStaging": false,
					"translator": {
						"type": "TabularTranslator",
						"typeConversion": true,
						"typeConversionSettings": {
							"allowDataTruncation": true,
							"treatBooleanAsNumber": false
						}
					}
				},
				"inputs": [
					{
						"referenceName": "ds_cases_deaths_source",
						"type": "DatasetReference",
						"parameters": {
							"relativeURL": {
								"value": "@pipeline().parameters.sourceRelativeURL",
								"type": "Expression"
							}
						}
					}
				],
				"outputs": [
					{
						"referenceName": "ds_cases_deaths_target",
						"type": "DatasetReference",
						"parameters": {
							"fileName": {
								"value": "@pipeline().parameters.sinkFileName",
								"type": "Expression"
							}
						}
					}
				]
			}
		],
		"parameters": {
			"sourceRelativeURL": {
				"type": "string"
			},
			"sinkFileName": {
				"type": "string"
			}
		},
		"annotations": []
	}
}